passtorage/__main2__.py
passtorage/__main__.py
passtorage/data/icon.ico
passtorage/data/reg/test
passtorage-0.0.4.dist-info/LICENSE
passtorage-0.0.4.dist-info/METADATA
passtorage-0.0.4.dist-info/WHEEL
passtorage-0.0.4.dist-info/entry_points.txt
passtorage-0.0.4.dist-info/top_level.txt
passtorage-0.0.4.dist-info/RECORD
