Metadata-Version: 2.1
Name: passtorage
Version: 0.0.4
Summary: txt password generator and manager with tkinter.
Home-page: https://github.com/Matipretz/passtorage
Author: Matías Pretz
Author-email: matipretz@gmail.com
License: MIT
Platform: Win10
Classifier: Environment :: Win32 (MS Windows)
Classifier: Intended Audience :: End Users/Desktop
Classifier: License :: OSI Approved :: MIT License
Classifier: Natural Language :: English
Classifier: Operating System :: Microsoft :: Windows :: Windows 10
Classifier: Programming Language :: Python :: 3.7
Classifier: Topic :: Security
Classifier: Topic :: Utilities
Requires: tkinter
Requires: random
Requires: pyperclip
